pyscaffoldext/__init__.py
pyscaffoldext/dsproject_vscode/__init__.py
pyscaffoldext/dsproject_vscode/extension.py
pyscaffoldext/dsproject_vscode/templates/__init__.py
pyscaffoldext/dsproject_vscode/templates/devcontainer_json.template
pyscaffoldext/dsproject_vscode/templates/devcontainer_local_json.template
pyscaffoldext/dsproject_vscode/templates/devcontainer_remote_json.template
pyscaffoldext/dsproject_vscode/templates/docker_compose_remote_yml.template
pyscaffoldext/dsproject_vscode/templates/docker_compose_yml.template
pyscaffoldext/dsproject_vscode/templates/dockerfile_dev_base.template
pyscaffoldext/dsproject_vscode/templates/environment_dev_base_yml.template
pyscaffoldext/dsproject_vscode/templates/gitignore_all.template
pyscaffoldext/dsproject_vscode/templates/gitignore_data.template
pyscaffoldext/dsproject_vscode/templates/gitkeep.template
pyscaffoldext/dsproject_vscode/templates/path_env.template
pyscaffoldext/dsproject_vscode/templates/readme_md.template
pyscaffoldext/dsproject_vscode/templates/settings_json.template
pyscaffoldext/dsproject_vscode/templates/template_ipynb.template
pyscaffoldext/dsproject_vscode/templates/train_model_py.template
pyscaffoldext_dsproject_vscode-0.1.4.dist-info/AUTHORS.rst
pyscaffoldext_dsproject_vscode-0.1.4.dist-info/LICENSE.txt
pyscaffoldext_dsproject_vscode-0.1.4.dist-info/METADATA
pyscaffoldext_dsproject_vscode-0.1.4.dist-info/WHEEL
pyscaffoldext_dsproject_vscode-0.1.4.dist-info/entry_points.txt
pyscaffoldext_dsproject_vscode-0.1.4.dist-info/top_level.txt
pyscaffoldext_dsproject_vscode-0.1.4.dist-info/RECORD
