Metadata-Version: 2.1
Name: pyscaffoldext-dsproject-vscode
Version: 0.1.4
Summary: PyScaffold extension for Data Science projects with VS Code container integration
Home-page: https://github.com/avsolatorio/pyscaffoldext-dsproject-vscode
Author: Aivin V. Solatorio
Author-email: avsolatorio@gmail.com
License: mit
Download-URL: https://github.com/avsolatorio/pyscaffoldext-dsproject-vscode/archive/v0.1.4.tar.gz
Project-URL: Documentation, https://pyscaffold.org/
Platform: any
Classifier: Development Status :: 4 - Beta
Classifier: Programming Language :: Python
Requires-Dist: pyscaffold (<4.0a0,>=3.2a0)
Requires-Dist: pyscaffoldext-markdown
Provides-Extra: testing
Requires-Dist: flake8 ; extra == 'testing'
Requires-Dist: pytest ; extra == 'testing'
Requires-Dist: pytest-cov ; extra == 'testing'
Requires-Dist: pytest-virtualenv ; extra == 'testing'
Requires-Dist: pytest-xdist ; extra == 'testing'
